setup.cfg
setup.py
seishub/__init__.py
seishub.plugins.exupery.egg-info/PKG-INFO
seishub.plugins.exupery.egg-info/SOURCES.txt
seishub.plugins.exupery.egg-info/dependency_links.txt
seishub.plugins.exupery.egg-info/entry_points.txt
seishub.plugins.exupery.egg-info/namespace_packages.txt
seishub.plugins.exupery.egg-info/not-zip-safe
seishub.plugins.exupery.egg-info/requires.txt
seishub.plugins.exupery.egg-info/top_level.txt
seishub/plugins/__init__.py
seishub/plugins/exupery/LICENSE.txt
seishub/plugins/exupery/README.txt
seishub/plugins/exupery/VERSION.txt
seishub/plugins/exupery/__init__.py
seishub/plugins/exupery/alertlevel.py
seishub/plugins/exupery/gis.py
seishub/plugins/exupery/gps.py
seishub/plugins/exupery/ibis.py
seishub/plugins/exupery/infrared.py
seishub/plugins/exupery/insar.py
seishub/plugins/exupery/minidoas.py
seishub/plugins/exupery/modis.py
seishub/plugins/exupery/mogi.py
seishub/plugins/exupery/package.py
seishub/plugins/exupery/psi.py
seishub/plugins/exupery/seismic.py
seishub/plugins/exupery/so2.py
seishub/plugins/exupery/xsd/gps-data.xsd
seishub/plugins/exupery/xsd/gps-station.xsd
seishub/plugins/exupery/xsd/ibis.xsd
seishub/plugins/exupery/xsd/infrared.xsd
seishub/plugins/exupery/xsd/insar.xsd
seishub/plugins/exupery/xsd/minidoas-data.xsd
seishub/plugins/exupery/xsd/psi.xsd
seishub/plugins/exupery/xsd/so2-gome2.xsd
seishub/plugins/exupery/xsd/so2-traj-disp.xsd
seishub/plugins/exupery/xslt/alert-level_metadata.xslt
seishub/plugins/exupery/xslt/alert-level_smile.xslt
seishub/plugins/exupery/xslt/gps-data_displacement.xslt
seishub/plugins/exupery/xslt/gps-data_metadata.xslt
seishub/plugins/exupery/xslt/gps-station_metadata.xslt
seishub/plugins/exupery/xslt/ibis_displacement_metadata.xslt
seishub/plugins/exupery/xslt/ibis_metadata.xslt
seishub/plugins/exupery/xslt/infrared_hotspots_metadata.xslt
seishub/plugins/exupery/xslt/insar_differential_metadata.xslt
seishub/plugins/exupery/xslt/insar_displacement_metadata.xslt
seishub/plugins/exupery/xslt/insar_interferogram_metadata.xslt
seishub/plugins/exupery/xslt/minidoas-station_metadata.xslt
seishub/plugins/exupery/xslt/modis_aqua_metadata.xslt
seishub/plugins/exupery/xslt/modis_terra_metadata.xslt
seishub/plugins/exupery/xslt/so2-gome2_metadata.xslt
seishub/plugins/exupery/xslt/so2-traj-disp_kml.xslt
seishub/plugins/exupery/xslt/so2-traj-disp_metadata.xslt